{
  "version": "6",
  "dialect": "sqlite",
  "id": "ed081cb4-fd84-453d-b10a-df4a346f8a9c",
  "prevId": "00000000-0000-0000-0000-000000000000",
  "tables": {
    "bahan_kajian": {
      "name": "bahan_kajian",
      "columns": {
        "id": {
          "name": "id",
          "type": "text",
          "primaryKey": true,
          "notNull": true,
          "autoincrement": false
        },
        "kode_bk": {
          "name": "kode_bk",
          "type": "text",
          "primaryKey": false,
          "notNull": true,
          "autoincrement": false
        },
        "nama_bahan_kajian": {
          "name": "nama_bahan_kajian",
          "type": "text",
          "primaryKey": false,
          "notNull": true,
          "autoincrement": false
        },
        "aspek": {
          "name": "aspek",
          "type": "text",
          "primaryKey": false,
          "notNull": true,
          "autoincrement": false
        },
        "ranah_keilmuan": {
          "name": "ranah_keilmuan",
          "type": "text",
          "primaryKey": false,
          "notNull": true,
          "autoincrement": false
        },
        "id_kurikulum": {
          "name": "id_kurikulum",
          "type": "text",
          "primaryKey": false,
          "notNull": true,
          "autoincrement": false
        },
        "created_at": {
          "name": "created_at",
          "type": "integer",
          "primaryKey": false,
          "notNull": true,
          "autoincrement": false,
          "default": "(unixepoch())"
        },
        "updated_at": {
          "name": "updated_at",
          "type": "integer",
          "primaryKey": false,
          "notNull": true,
          "autoincrement": false,
          "default": "(unixepoch())"
        }
      },
      "indexes": {},
      "foreignKeys": {
        "bahan_kajian_id_kurikulum_kurikulum_id_fk": {
          "name": "bahan_kajian_id_kurikulum_kurikulum_id_fk",
          "tableFrom": "bahan_kajian",
          "tableTo": "kurikulum",
          "columnsFrom": [
            "id_kurikulum"
          ],
          "columnsTo": [
            "id"
          ],
          "onDelete": "no action",
          "onUpdate": "no action"
        }
      },
      "compositePrimaryKeys": {},
      "uniqueConstraints": {},
      "checkConstraints": {}
    },
    "cpl": {
      "name": "cpl",
      "columns": {
        "id": {
          "name": "id",
          "type": "text",
          "primaryKey": true,
          "notNull": true,
          "autoincrement": false
        },
        "kode_cpl": {
          "name": "kode_cpl",
          "type": "text",
          "primaryKey": false,
          "notNull": true,
          "autoincrement": false
        },
        "deskripsi_cpl": {
          "name": "deskripsi_cpl",
          "type": "text",
          "primaryKey": false,
          "notNull": true,
          "autoincrement": false
        },
        "aspek": {
          "name": "aspek",
          "type": "text",
          "primaryKey": false,
          "notNull": true,
          "autoincrement": false
        },
        "id_kurikulum": {
          "name": "id_kurikulum",
          "type": "text",
          "primaryKey": false,
          "notNull": true,
          "autoincrement": false
        },
        "created_at": {
          "name": "created_at",
          "type": "integer",
          "primaryKey": false,
          "notNull": true,
          "autoincrement": false,
          "default": "(unixepoch())"
        },
        "updated_at": {
          "name": "updated_at",
          "type": "integer",
          "primaryKey": false,
          "notNull": true,
          "autoincrement": false,
          "default": "(unixepoch())"
        }
      },
      "indexes": {},
      "foreignKeys": {
        "cpl_id_kurikulum_kurikulum_id_fk": {
          "name": "cpl_id_kurikulum_kurikulum_id_fk",
          "tableFrom": "cpl",
          "tableTo": "kurikulum",
          "columnsFrom": [
            "id_kurikulum"
          ],
          "columnsTo": [
            "id"
          ],
          "onDelete": "no action",
          "onUpdate": "no action"
        }
      },
      "compositePrimaryKeys": {},
      "uniqueConstraints": {},
      "checkConstraints": {}
    },
    "cpmk": {
      "name": "cpmk",
      "columns": {
        "id": {
          "name": "id",
          "type": "text",
          "primaryKey": true,
          "notNull": true,
          "autoincrement": false
        },
        "kode_cpmk": {
          "name": "kode_cpmk",
          "type": "text",
          "primaryKey": false,
          "notNull": true,
          "autoincrement": false
        },
        "deskripsi_cpmk": {
          "name": "deskripsi_cpmk",
          "type": "text",
          "primaryKey": false,
          "notNull": true,
          "autoincrement": false
        },
        "bobot_persentase": {
          "name": "bobot_persentase",
          "type": "real",
          "primaryKey": false,
          "notNull": true,
          "autoincrement": false
        },
        "id_mk": {
          "name": "id_mk",
          "type": "text",
          "primaryKey": false,
          "notNull": true,
          "autoincrement": false
        },
        "id_cpl": {
          "name": "id_cpl",
          "type": "text",
          "primaryKey": false,
          "notNull": true,
          "autoincrement": false
        },
        "created_at": {
          "name": "created_at",
          "type": "integer",
          "primaryKey": false,
          "notNull": true,
          "autoincrement": false,
          "default": "(unixepoch())"
        },
        "updated_at": {
          "name": "updated_at",
          "type": "integer",
          "primaryKey": false,
          "notNull": true,
          "autoincrement": false,
          "default": "(unixepoch())"
        }
      },
      "indexes": {},
      "foreignKeys": {
        "cpmk_id_mk_mata_kuliah_id_fk": {
          "name": "cpmk_id_mk_mata_kuliah_id_fk",
          "tableFrom": "cpmk",
          "tableTo": "mata_kuliah",
          "columnsFrom": [
            "id_mk"
          ],
          "columnsTo": [
            "id"
          ],
          "onDelete": "cascade",
          "onUpdate": "no action"
        },
        "cpmk_id_cpl_cpl_id_fk": {
          "name": "cpmk_id_cpl_cpl_id_fk",
          "tableFrom": "cpmk",
          "tableTo": "cpl",
          "columnsFrom": [
            "id_cpl"
          ],
          "columnsTo": [
            "id"
          ],
          "onDelete": "no action",
          "onUpdate": "no action"
        }
      },
      "compositePrimaryKeys": {},
      "uniqueConstraints": {},
      "checkConstraints": {}
    },
    "dosen": {
      "name": "dosen",
      "columns": {
        "id": {
          "name": "id",
          "type": "text",
          "primaryKey": true,
          "notNull": true,
          "autoincrement": false
        },
        "nip": {
          "name": "nip",
          "type": "text",
          "primaryKey": false,
          "notNull": true,
          "autoincrement": false
        },
        "nama_dosen": {
          "name": "nama_dosen",
          "type": "text",
          "primaryKey": false,
          "notNull": true,
          "autoincrement": false
        },
        "email": {
          "name": "email",
          "type": "text",
          "primaryKey": false,
          "notNull": false,
          "autoincrement": false
        },
        "bidang_keahlian": {
          "name": "bidang_keahlian",
          "type": "text",
          "primaryKey": false,
          "notNull": false,
          "autoincrement": false
        },
        "jabatan_fungsional": {
          "name": "jabatan_fungsional",
          "type": "text",
          "primaryKey": false,
          "notNull": false,
          "autoincrement": false
        },
        "id_prodi": {
          "name": "id_prodi",
          "type": "text",
          "primaryKey": false,
          "notNull": false,
          "autoincrement": false
        },
        "id_user": {
          "name": "id_user",
          "type": "text",
          "primaryKey": false,
          "notNull": false,
          "autoincrement": false
        },
        "created_at": {
          "name": "created_at",
          "type": "integer",
          "primaryKey": false,
          "notNull": true,
          "autoincrement": false,
          "default": "(unixepoch())"
        },
        "updated_at": {
          "name": "updated_at",
          "type": "integer",
          "primaryKey": false,
          "notNull": true,
          "autoincrement": false,
          "default": "(unixepoch())"
        }
      },
      "indexes": {
        "dosen_nip_unique": {
          "name": "dosen_nip_unique",
          "columns": [
            "nip"
          ],
          "isUnique": true
        }
      },
      "foreignKeys": {
        "dosen_id_prodi_prodi_id_fk": {
          "name": "dosen_id_prodi_prodi_id_fk",
          "tableFrom": "dosen",
          "tableTo": "prodi",
          "columnsFrom": [
            "id_prodi"
          ],
          "columnsTo": [
            "id"
          ],
          "onDelete": "no action",
          "onUpdate": "no action"
        },
        "dosen_id_user_users_id_fk": {
          "name": "dosen_id_user_users_id_fk",
          "tableFrom": "dosen",
          "tableTo": "users",
          "columnsFrom": [
            "id_user"
          ],
          "columnsTo": [
            "id"
          ],
          "onDelete": "no action",
          "onUpdate": "no action"
        }
      },
      "compositePrimaryKeys": {},
      "uniqueConstraints": {},
      "checkConstraints": {}
    },
    "kompetensi_utama": {
      "name": "kompetensi_utama",
      "columns": {
        "id": {
          "name": "id",
          "type": "text",
          "primaryKey": true,
          "notNull": true,
          "autoincrement": false
        },
        "kode_kul": {
          "name": "kode_kul",
          "type": "text",
          "primaryKey": false,
          "notNull": true,
          "autoincrement": false
        },
        "kompetensi_lulusan": {
          "name": "kompetensi_lulusan",
          "type": "text",
          "primaryKey": false,
          "notNull": true,
          "autoincrement": false
        },
        "aspek": {
          "name": "aspek",
          "type": "text",
          "primaryKey": false,
          "notNull": true,
          "autoincrement": false
        },
        "id_kurikulum": {
          "name": "id_kurikulum",
          "type": "text",
          "primaryKey": false,
          "notNull": true,
          "autoincrement": false
        },
        "created_at": {
          "name": "created_at",
          "type": "integer",
          "primaryKey": false,
          "notNull": true,
          "autoincrement": false,
          "default": "(unixepoch())"
        },
        "updated_at": {
          "name": "updated_at",
          "type": "integer",
          "primaryKey": false,
          "notNull": true,
          "autoincrement": false,
          "default": "(unixepoch())"
        }
      },
      "indexes": {},
      "foreignKeys": {
        "kompetensi_utama_id_kurikulum_kurikulum_id_fk": {
          "name": "kompetensi_utama_id_kurikulum_kurikulum_id_fk",
          "tableFrom": "kompetensi_utama",
          "tableTo": "kurikulum",
          "columnsFrom": [
            "id_kurikulum"
          ],
          "columnsTo": [
            "id"
          ],
          "onDelete": "no action",
          "onUpdate": "no action"
        }
      },
      "compositePrimaryKeys": {},
      "uniqueConstraints": {},
      "checkConstraints": {}
    },
    "kurikulum": {
      "name": "kurikulum",
      "columns": {
        "id": {
          "name": "id",
          "type": "text",
          "primaryKey": true,
          "notNull": true,
          "autoincrement": false
        },
        "nama_kurikulum": {
          "name": "nama_kurikulum",
          "type": "text",
          "primaryKey": false,
          "notNull": true,
          "autoincrement": false
        },
        "tahun_berlaku": {
          "name": "tahun_berlaku",
          "type": "integer",
          "primaryKey": false,
          "notNull": true,
          "autoincrement": false
        },
        "is_active": {
          "name": "is_active",
          "type": "integer",
          "primaryKey": false,
          "notNull": true,
          "autoincrement": false,
          "default": false
        },
        "id_prodi": {
          "name": "id_prodi",
          "type": "text",
          "primaryKey": false,
          "notNull": true,
          "autoincrement": false
        },
        "created_at": {
          "name": "created_at",
          "type": "integer",
          "primaryKey": false,
          "notNull": true,
          "autoincrement": false,
          "default": "(unixepoch())"
        },
        "updated_at": {
          "name": "updated_at",
          "type": "integer",
          "primaryKey": false,
          "notNull": true,
          "autoincrement": false,
          "default": "(unixepoch())"
        }
      },
      "indexes": {},
      "foreignKeys": {
        "kurikulum_id_prodi_prodi_id_fk": {
          "name": "kurikulum_id_prodi_prodi_id_fk",
          "tableFrom": "kurikulum",
          "tableTo": "prodi",
          "columnsFrom": [
            "id_prodi"
          ],
          "columnsTo": [
            "id"
          ],
          "onDelete": "no action",
          "onUpdate": "no action"
        }
      },
      "compositePrimaryKeys": {},
      "uniqueConstraints": {},
      "checkConstraints": {}
    },
    "mata_kuliah": {
      "name": "mata_kuliah",
      "columns": {
        "id": {
          "name": "id",
          "type": "text",
          "primaryKey": true,
          "notNull": true,
          "autoincrement": false
        },
        "kode_mk": {
          "name": "kode_mk",
          "type": "text",
          "primaryKey": false,
          "notNull": true,
          "autoincrement": false
        },
        "nama_mk": {
          "name": "nama_mk",
          "type": "text",
          "primaryKey": false,
          "notNull": true,
          "autoincrement": false
        },
        "sks": {
          "name": "sks",
          "type": "integer",
          "primaryKey": false,
          "notNull": true,
          "autoincrement": false
        },
        "semester": {
          "name": "semester",
          "type": "integer",
          "primaryKey": false,
          "notNull": true,
          "autoincrement": false
        },
        "sifat": {
          "name": "sifat",
          "type": "text",
          "primaryKey": false,
          "notNull": true,
          "autoincrement": false
        },
        "deskripsi": {
          "name": "deskripsi",
          "type": "text",
          "primaryKey": false,
          "notNull": false,
          "autoincrement": false
        },
        "id_kurikulum": {
          "name": "id_kurikulum",
          "type": "text",
          "primaryKey": false,
          "notNull": true,
          "autoincrement": false
        },
        "id_bahan_kajian": {
          "name": "id_bahan_kajian",
          "type": "text",
          "primaryKey": false,
          "notNull": false,
          "autoincrement": false
        },
        "created_at": {
          "name": "created_at",
          "type": "integer",
          "primaryKey": false,
          "notNull": true,
          "autoincrement": false,
          "default": "(unixepoch())"
        },
        "updated_at": {
          "name": "updated_at",
          "type": "integer",
          "primaryKey": false,
          "notNull": true,
          "autoincrement": false,
          "default": "(unixepoch())"
        }
      },
      "indexes": {
        "mata_kuliah_kode_mk_unique": {
          "name": "mata_kuliah_kode_mk_unique",
          "columns": [
            "kode_mk"
          ],
          "isUnique": true
        }
      },
      "foreignKeys": {
        "mata_kuliah_id_kurikulum_kurikulum_id_fk": {
          "name": "mata_kuliah_id_kurikulum_kurikulum_id_fk",
          "tableFrom": "mata_kuliah",
          "tableTo": "kurikulum",
          "columnsFrom": [
            "id_kurikulum"
          ],
          "columnsTo": [
            "id"
          ],
          "onDelete": "no action",
          "onUpdate": "no action"
        },
        "mata_kuliah_id_bahan_kajian_bahan_kajian_id_fk": {
          "name": "mata_kuliah_id_bahan_kajian_bahan_kajian_id_fk",
          "tableFrom": "mata_kuliah",
          "tableTo": "bahan_kajian",
          "columnsFrom": [
            "id_bahan_kajian"
          ],
          "columnsTo": [
            "id"
          ],
          "onDelete": "no action",
          "onUpdate": "no action"
        }
      },
      "compositePrimaryKeys": {},
      "uniqueConstraints": {},
      "checkConstraints": {}
    },
    "matrix_cpl_bk": {
      "name": "matrix_cpl_bk",
      "columns": {
        "id": {
          "name": "id",
          "type": "text",
          "primaryKey": true,
          "notNull": true,
          "autoincrement": false
        },
        "id_cpl": {
          "name": "id_cpl",
          "type": "text",
          "primaryKey": false,
          "notNull": true,
          "autoincrement": false
        },
        "id_bk": {
          "name": "id_bk",
          "type": "text",
          "primaryKey": false,
          "notNull": true,
          "autoincrement": false
        },
        "created_at": {
          "name": "created_at",
          "type": "integer",
          "primaryKey": false,
          "notNull": true,
          "autoincrement": false,
          "default": "(unixepoch())"
        }
      },
      "indexes": {},
      "foreignKeys": {
        "matrix_cpl_bk_id_cpl_cpl_id_fk": {
          "name": "matrix_cpl_bk_id_cpl_cpl_id_fk",
          "tableFrom": "matrix_cpl_bk",
          "tableTo": "cpl",
          "columnsFrom": [
            "id_cpl"
          ],
          "columnsTo": [
            "id"
          ],
          "onDelete": "cascade",
          "onUpdate": "no action"
        },
        "matrix_cpl_bk_id_bk_bahan_kajian_id_fk": {
          "name": "matrix_cpl_bk_id_bk_bahan_kajian_id_fk",
          "tableFrom": "matrix_cpl_bk",
          "tableTo": "bahan_kajian",
          "columnsFrom": [
            "id_bk"
          ],
          "columnsTo": [
            "id"
          ],
          "onDelete": "cascade",
          "onUpdate": "no action"
        }
      },
      "compositePrimaryKeys": {},
      "uniqueConstraints": {},
      "checkConstraints": {}
    },
    "matrix_cpl_mk": {
      "name": "matrix_cpl_mk",
      "columns": {
        "id": {
          "name": "id",
          "type": "text",
          "primaryKey": true,
          "notNull": true,
          "autoincrement": false
        },
        "id_cpl": {
          "name": "id_cpl",
          "type": "text",
          "primaryKey": false,
          "notNull": true,
          "autoincrement": false
        },
        "id_mk": {
          "name": "id_mk",
          "type": "text",
          "primaryKey": false,
          "notNull": true,
          "autoincrement": false
        },
        "created_at": {
          "name": "created_at",
          "type": "integer",
          "primaryKey": false,
          "notNull": true,
          "autoincrement": false,
          "default": "(unixepoch())"
        }
      },
      "indexes": {},
      "foreignKeys": {
        "matrix_cpl_mk_id_cpl_cpl_id_fk": {
          "name": "matrix_cpl_mk_id_cpl_cpl_id_fk",
          "tableFrom": "matrix_cpl_mk",
          "tableTo": "cpl",
          "columnsFrom": [
            "id_cpl"
          ],
          "columnsTo": [
            "id"
          ],
          "onDelete": "cascade",
          "onUpdate": "no action"
        },
        "matrix_cpl_mk_id_mk_mata_kuliah_id_fk": {
          "name": "matrix_cpl_mk_id_mk_mata_kuliah_id_fk",
          "tableFrom": "matrix_cpl_mk",
          "tableTo": "mata_kuliah",
          "columnsFrom": [
            "id_mk"
          ],
          "columnsTo": [
            "id"
          ],
          "onDelete": "cascade",
          "onUpdate": "no action"
        }
      },
      "compositePrimaryKeys": {},
      "uniqueConstraints": {},
      "checkConstraints": {}
    },
    "matrix_cpl_pl": {
      "name": "matrix_cpl_pl",
      "columns": {
        "id": {
          "name": "id",
          "type": "text",
          "primaryKey": true,
          "notNull": true,
          "autoincrement": false
        },
        "id_cpl": {
          "name": "id_cpl",
          "type": "text",
          "primaryKey": false,
          "notNull": true,
          "autoincrement": false
        },
        "id_profil": {
          "name": "id_profil",
          "type": "text",
          "primaryKey": false,
          "notNull": true,
          "autoincrement": false
        },
        "created_at": {
          "name": "created_at",
          "type": "integer",
          "primaryKey": false,
          "notNull": true,
          "autoincrement": false,
          "default": "(unixepoch())"
        }
      },
      "indexes": {},
      "foreignKeys": {
        "matrix_cpl_pl_id_cpl_cpl_id_fk": {
          "name": "matrix_cpl_pl_id_cpl_cpl_id_fk",
          "tableFrom": "matrix_cpl_pl",
          "tableTo": "cpl",
          "columnsFrom": [
            "id_cpl"
          ],
          "columnsTo": [
            "id"
          ],
          "onDelete": "cascade",
          "onUpdate": "no action"
        },
        "matrix_cpl_pl_id_profil_profil_lulusan_id_fk": {
          "name": "matrix_cpl_pl_id_profil_profil_lulusan_id_fk",
          "tableFrom": "matrix_cpl_pl",
          "tableTo": "profil_lulusan",
          "columnsFrom": [
            "id_profil"
          ],
          "columnsTo": [
            "id"
          ],
          "onDelete": "cascade",
          "onUpdate": "no action"
        }
      },
      "compositePrimaryKeys": {},
      "uniqueConstraints": {},
      "checkConstraints": {}
    },
    "penugasan_dosen": {
      "name": "penugasan_dosen",
      "columns": {
        "id": {
          "name": "id",
          "type": "text",
          "primaryKey": true,
          "notNull": true,
          "autoincrement": false
        },
        "id_mk": {
          "name": "id_mk",
          "type": "text",
          "primaryKey": false,
          "notNull": true,
          "autoincrement": false
        },
        "id_dosen": {
          "name": "id_dosen",
          "type": "text",
          "primaryKey": false,
          "notNull": true,
          "autoincrement": false
        },
        "is_koordinator": {
          "name": "is_koordinator",
          "type": "integer",
          "primaryKey": false,
          "notNull": true,
          "autoincrement": false,
          "default": false
        },
        "tahun_akademik": {
          "name": "tahun_akademik",
          "type": "text",
          "primaryKey": false,
          "notNull": true,
          "autoincrement": false
        },
        "semester_akademik": {
          "name": "semester_akademik",
          "type": "text",
          "primaryKey": false,
          "notNull": true,
          "autoincrement": false
        },
        "created_at": {
          "name": "created_at",
          "type": "integer",
          "primaryKey": false,
          "notNull": true,
          "autoincrement": false,
          "default": "(unixepoch())"
        }
      },
      "indexes": {},
      "foreignKeys": {
        "penugasan_dosen_id_mk_mata_kuliah_id_fk": {
          "name": "penugasan_dosen_id_mk_mata_kuliah_id_fk",
          "tableFrom": "penugasan_dosen",
          "tableTo": "mata_kuliah",
          "columnsFrom": [
            "id_mk"
          ],
          "columnsTo": [
            "id"
          ],
          "onDelete": "cascade",
          "onUpdate": "no action"
        },
        "penugasan_dosen_id_dosen_dosen_id_fk": {
          "name": "penugasan_dosen_id_dosen_dosen_id_fk",
          "tableFrom": "penugasan_dosen",
          "tableTo": "dosen",
          "columnsFrom": [
            "id_dosen"
          ],
          "columnsTo": [
            "id"
          ],
          "onDelete": "cascade",
          "onUpdate": "no action"
        }
      },
      "compositePrimaryKeys": {},
      "uniqueConstraints": {},
      "checkConstraints": {}
    },
    "prodi": {
      "name": "prodi",
      "columns": {
        "id": {
          "name": "id",
          "type": "text",
          "primaryKey": true,
          "notNull": true,
          "autoincrement": false
        },
        "kode_prodi": {
          "name": "kode_prodi",
          "type": "text",
          "primaryKey": false,
          "notNull": true,
          "autoincrement": false
        },
        "nama_prodi": {
          "name": "nama_prodi",
          "type": "text",
          "primaryKey": false,
          "notNull": true,
          "autoincrement": false
        },
        "fakultas": {
          "name": "fakultas",
          "type": "text",
          "primaryKey": false,
          "notNull": true,
          "autoincrement": false
        },
        "jenjang": {
          "name": "jenjang",
          "type": "text",
          "primaryKey": false,
          "notNull": true,
          "autoincrement": false
        },
        "akreditasi": {
          "name": "akreditasi",
          "type": "text",
          "primaryKey": false,
          "notNull": false,
          "autoincrement": false
        },
        "created_at": {
          "name": "created_at",
          "type": "integer",
          "primaryKey": false,
          "notNull": true,
          "autoincrement": false,
          "default": "(unixepoch())"
        },
        "updated_at": {
          "name": "updated_at",
          "type": "integer",
          "primaryKey": false,
          "notNull": true,
          "autoincrement": false,
          "default": "(unixepoch())"
        }
      },
      "indexes": {
        "prodi_kode_prodi_unique": {
          "name": "prodi_kode_prodi_unique",
          "columns": [
            "kode_prodi"
          ],
          "isUnique": true
        }
      },
      "foreignKeys": {},
      "compositePrimaryKeys": {},
      "uniqueConstraints": {},
      "checkConstraints": {}
    },
    "profil_lulusan": {
      "name": "profil_lulusan",
      "columns": {
        "id": {
          "name": "id",
          "type": "text",
          "primaryKey": true,
          "notNull": true,
          "autoincrement": false
        },
        "kode_profil": {
          "name": "kode_profil",
          "type": "text",
          "primaryKey": false,
          "notNull": true,
          "autoincrement": false
        },
        "profil_lulusan": {
          "name": "profil_lulusan",
          "type": "text",
          "primaryKey": false,
          "notNull": true,
          "autoincrement": false
        },
        "deskripsi": {
          "name": "deskripsi",
          "type": "text",
          "primaryKey": false,
          "notNull": true,
          "autoincrement": false
        },
        "sumber": {
          "name": "sumber",
          "type": "text",
          "primaryKey": false,
          "notNull": true,
          "autoincrement": false
        },
        "id_kurikulum": {
          "name": "id_kurikulum",
          "type": "text",
          "primaryKey": false,
          "notNull": true,
          "autoincrement": false
        },
        "created_at": {
          "name": "created_at",
          "type": "integer",
          "primaryKey": false,
          "notNull": true,
          "autoincrement": false,
          "default": "(unixepoch())"
        },
        "updated_at": {
          "name": "updated_at",
          "type": "integer",
          "primaryKey": false,
          "notNull": true,
          "autoincrement": false,
          "default": "(unixepoch())"
        }
      },
      "indexes": {},
      "foreignKeys": {
        "profil_lulusan_id_kurikulum_kurikulum_id_fk": {
          "name": "profil_lulusan_id_kurikulum_kurikulum_id_fk",
          "tableFrom": "profil_lulusan",
          "tableTo": "kurikulum",
          "columnsFrom": [
            "id_kurikulum"
          ],
          "columnsTo": [
            "id"
          ],
          "onDelete": "no action",
          "onUpdate": "no action"
        }
      },
      "compositePrimaryKeys": {},
      "uniqueConstraints": {},
      "checkConstraints": {}
    },
    "rps": {
      "name": "rps",
      "columns": {
        "id": {
          "name": "id",
          "type": "text",
          "primaryKey": true,
          "notNull": true,
          "autoincrement": false
        },
        "id_mk": {
          "name": "id_mk",
          "type": "text",
          "primaryKey": false,
          "notNull": true,
          "autoincrement": false
        },
        "versi": {
          "name": "versi",
          "type": "integer",
          "primaryKey": false,
          "notNull": true,
          "autoincrement": false,
          "default": 1
        },
        "tahun_akademik": {
          "name": "tahun_akademik",
          "type": "text",
          "primaryKey": false,
          "notNull": true,
          "autoincrement": false
        },
        "semester_akademik": {
          "name": "semester_akademik",
          "type": "text",
          "primaryKey": false,
          "notNull": true,
          "autoincrement": false
        },
        "tgl_penyusunan": {
          "name": "tgl_penyusunan",
          "type": "integer",
          "primaryKey": false,
          "notNull": false,
          "autoincrement": false
        },
        "tgl_validasi": {
          "name": "tgl_validasi",
          "type": "integer",
          "primaryKey": false,
          "notNull": false,
          "autoincrement": false
        },
        "status": {
          "name": "status",
          "type": "text",
          "primaryKey": false,
          "notNull": true,
          "autoincrement": false,
          "default": "'Draft'"
        },
        "deskripsi_mk": {
          "name": "deskripsi_mk",
          "type": "text",
          "primaryKey": false,
          "notNull": false,
          "autoincrement": false
        },
        "pustaka_utama": {
          "name": "pustaka_utama",
          "type": "text",
          "primaryKey": false,
          "notNull": false,
          "autoincrement": false
        },
        "pustaka_pendukung": {
          "name": "pustaka_pendukung",
          "type": "text",
          "primaryKey": false,
          "notNull": false,
          "autoincrement": false
        },
        "id_koordinator": {
          "name": "id_koordinator",
          "type": "text",
          "primaryKey": false,
          "notNull": false,
          "autoincrement": false
        },
        "id_kaprodi": {
          "name": "id_kaprodi",
          "type": "text",
          "primaryKey": false,
          "notNull": false,
          "autoincrement": false
        },
        "created_at": {
          "name": "created_at",
          "type": "integer",
          "primaryKey": false,
          "notNull": true,
          "autoincrement": false,
          "default": "(unixepoch())"
        },
        "updated_at": {
          "name": "updated_at",
          "type": "integer",
          "primaryKey": false,
          "notNull": true,
          "autoincrement": false,
          "default": "(unixepoch())"
        }
      },
      "indexes": {},
      "foreignKeys": {
        "rps_id_mk_mata_kuliah_id_fk": {
          "name": "rps_id_mk_mata_kuliah_id_fk",
          "tableFrom": "rps",
          "tableTo": "mata_kuliah",
          "columnsFrom": [
            "id_mk"
          ],
          "columnsTo": [
            "id"
          ],
          "onDelete": "no action",
          "onUpdate": "no action"
        },
        "rps_id_koordinator_dosen_id_fk": {
          "name": "rps_id_koordinator_dosen_id_fk",
          "tableFrom": "rps",
          "tableTo": "dosen",
          "columnsFrom": [
            "id_koordinator"
          ],
          "columnsTo": [
            "id"
          ],
          "onDelete": "no action",
          "onUpdate": "no action"
        },
        "rps_id_kaprodi_dosen_id_fk": {
          "name": "rps_id_kaprodi_dosen_id_fk",
          "tableFrom": "rps",
          "tableTo": "dosen",
          "columnsFrom": [
            "id_kaprodi"
          ],
          "columnsTo": [
            "id"
          ],
          "onDelete": "no action",
          "onUpdate": "no action"
        }
      },
      "compositePrimaryKeys": {},
      "uniqueConstraints": {},
      "checkConstraints": {}
    },
    "rps_minggu": {
      "name": "rps_minggu",
      "columns": {
        "id": {
          "name": "id",
          "type": "text",
          "primaryKey": true,
          "notNull": true,
          "autoincrement": false
        },
        "id_rps": {
          "name": "id_rps",
          "type": "text",
          "primaryKey": false,
          "notNull": true,
          "autoincrement": false
        },
        "minggu_ke": {
          "name": "minggu_ke",
          "type": "integer",
          "primaryKey": false,
          "notNull": true,
          "autoincrement": false
        },
        "id_sub_cpmk": {
          "name": "id_sub_cpmk",
          "type": "text",
          "primaryKey": false,
          "notNull": false,
          "autoincrement": false
        },
        "materi": {
          "name": "materi",
          "type": "text",
          "primaryKey": false,
          "notNull": true,
          "autoincrement": false
        },
        "metode_pembelajaran": {
          "name": "metode_pembelajaran",
          "type": "text",
          "primaryKey": false,
          "notNull": false,
          "autoincrement": false
        },
        "waktu_menit": {
          "name": "waktu_menit",
          "type": "integer",
          "primaryKey": false,
          "notNull": true,
          "autoincrement": false,
          "default": 150
        },
        "pengalaman_belajar": {
          "name": "pengalaman_belajar",
          "type": "text",
          "primaryKey": false,
          "notNull": false,
          "autoincrement": false
        },
        "bentuk_penilaian": {
          "name": "bentuk_penilaian",
          "type": "text",
          "primaryKey": false,
          "notNull": false,
          "autoincrement": false
        },
        "bobot_penilaian": {
          "name": "bobot_penilaian",
          "type": "real",
          "primaryKey": false,
          "notNull": false,
          "autoincrement": false
        },
        "created_at": {
          "name": "created_at",
          "type": "integer",
          "primaryKey": false,
          "notNull": true,
          "autoincrement": false,
          "default": "(unixepoch())"
        },
        "updated_at": {
          "name": "updated_at",
          "type": "integer",
          "primaryKey": false,
          "notNull": true,
          "autoincrement": false,
          "default": "(unixepoch())"
        }
      },
      "indexes": {},
      "foreignKeys": {
        "rps_minggu_id_rps_rps_id_fk": {
          "name": "rps_minggu_id_rps_rps_id_fk",
          "tableFrom": "rps_minggu",
          "tableTo": "rps",
          "columnsFrom": [
            "id_rps"
          ],
          "columnsTo": [
            "id"
          ],
          "onDelete": "cascade",
          "onUpdate": "no action"
        },
        "rps_minggu_id_sub_cpmk_sub_cpmk_id_fk": {
          "name": "rps_minggu_id_sub_cpmk_sub_cpmk_id_fk",
          "tableFrom": "rps_minggu",
          "tableTo": "sub_cpmk",
          "columnsFrom": [
            "id_sub_cpmk"
          ],
          "columnsTo": [
            "id"
          ],
          "onDelete": "no action",
          "onUpdate": "no action"
        }
      },
      "compositePrimaryKeys": {},
      "uniqueConstraints": {},
      "checkConstraints": {}
    },
    "sub_cpmk": {
      "name": "sub_cpmk",
      "columns": {
        "id": {
          "name": "id",
          "type": "text",
          "primaryKey": true,
          "notNull": true,
          "autoincrement": false
        },
        "kode_sub": {
          "name": "kode_sub",
          "type": "text",
          "primaryKey": false,
          "notNull": true,
          "autoincrement": false
        },
        "deskripsi_sub_cpmk": {
          "name": "deskripsi_sub_cpmk",
          "type": "text",
          "primaryKey": false,
          "notNull": true,
          "autoincrement": false
        },
        "indikator": {
          "name": "indikator",
          "type": "text",
          "primaryKey": false,
          "notNull": true,
          "autoincrement": false
        },
        "kriteria_penilaian": {
          "name": "kriteria_penilaian",
          "type": "text",
          "primaryKey": false,
          "notNull": true,
          "autoincrement": false
        },
        "id_cpmk": {
          "name": "id_cpmk",
          "type": "text",
          "primaryKey": false,
          "notNull": true,
          "autoincrement": false
        },
        "created_at": {
          "name": "created_at",
          "type": "integer",
          "primaryKey": false,
          "notNull": true,
          "autoincrement": false,
          "default": "(unixepoch())"
        },
        "updated_at": {
          "name": "updated_at",
          "type": "integer",
          "primaryKey": false,
          "notNull": true,
          "autoincrement": false,
          "default": "(unixepoch())"
        }
      },
      "indexes": {},
      "foreignKeys": {
        "sub_cpmk_id_cpmk_cpmk_id_fk": {
          "name": "sub_cpmk_id_cpmk_cpmk_id_fk",
          "tableFrom": "sub_cpmk",
          "tableTo": "cpmk",
          "columnsFrom": [
            "id_cpmk"
          ],
          "columnsTo": [
            "id"
          ],
          "onDelete": "cascade",
          "onUpdate": "no action"
        }
      },
      "compositePrimaryKeys": {},
      "uniqueConstraints": {},
      "checkConstraints": {}
    },
    "users": {
      "name": "users",
      "columns": {
        "id": {
          "name": "id",
          "type": "text",
          "primaryKey": true,
          "notNull": true,
          "autoincrement": false
        },
        "email": {
          "name": "email",
          "type": "text",
          "primaryKey": false,
          "notNull": true,
          "autoincrement": false
        },
        "password": {
          "name": "password",
          "type": "text",
          "primaryKey": false,
          "notNull": true,
          "autoincrement": false
        },
        "nama": {
          "name": "nama",
          "type": "text",
          "primaryKey": false,
          "notNull": true,
          "autoincrement": false
        },
        "role": {
          "name": "role",
          "type": "text",
          "primaryKey": false,
          "notNull": true,
          "autoincrement": false,
          "default": "'dosen'"
        },
        "id_prodi": {
          "name": "id_prodi",
          "type": "text",
          "primaryKey": false,
          "notNull": false,
          "autoincrement": false
        },
        "created_at": {
          "name": "created_at",
          "type": "integer",
          "primaryKey": false,
          "notNull": true,
          "autoincrement": false,
          "default": "(unixepoch())"
        },
        "updated_at": {
          "name": "updated_at",
          "type": "integer",
          "primaryKey": false,
          "notNull": true,
          "autoincrement": false,
          "default": "(unixepoch())"
        }
      },
      "indexes": {
        "users_email_unique": {
          "name": "users_email_unique",
          "columns": [
            "email"
          ],
          "isUnique": true
        }
      },
      "foreignKeys": {
        "users_id_prodi_prodi_id_fk": {
          "name": "users_id_prodi_prodi_id_fk",
          "tableFrom": "users",
          "tableTo": "prodi",
          "columnsFrom": [
            "id_prodi"
          ],
          "columnsTo": [
            "id"
          ],
          "onDelete": "no action",
          "onUpdate": "no action"
        }
      },
      "compositePrimaryKeys": {},
      "uniqueConstraints": {},
      "checkConstraints": {}
    }
  },
  "views": {},
  "enums": {},
  "_meta": {
    "schemas": {},
    "tables": {},
    "columns": {}
  },
  "internal": {
    "indexes": {}
  }
}